killbill/__init__.py
killbill/api_client.py
killbill/configuration.py
killbill/rest.py
killbill/api/__init__.py
killbill/api/account_api.py
killbill/api/admin_api.py
killbill/api/bundle_api.py
killbill/api/catalog_api.py
killbill/api/credit_api.py
killbill/api/custom_field_api.py
killbill/api/export_api.py
killbill/api/invoice_api.py
killbill/api/invoice_item_api.py
killbill/api/invoice_payment_api.py
killbill/api/nodes_info_api.py
killbill/api/overdue_api.py
killbill/api/payment_api.py
killbill/api/payment_gateway_api.py
killbill/api/payment_method_api.py
killbill/api/payment_transaction_api.py
killbill/api/plugin_info_api.py
killbill/api/security_api.py
killbill/api/subscription_api.py
killbill/api/tag_api.py
killbill/api/tag_definition_api.py
killbill/api/tenant_api.py
killbill/api/usage_api.py
killbill/models/__init__.py
killbill/models/account.py
killbill/models/account_email.py
killbill/models/account_timeline.py
killbill/models/admin_payment.py
killbill/models/audit_log.py
killbill/models/block_price.py
killbill/models/blocking_state.py
killbill/models/bulk_subscriptions_bundle.py
killbill/models/bundle.py
killbill/models/bundle_timeline.py
killbill/models/catalog.py
killbill/models/combo_hosted_payment_page.py
killbill/models/combo_payment_transaction.py
killbill/models/custom_field.py
killbill/models/duration.py
killbill/models/entity.py
killbill/models/event_subscription.py
killbill/models/hosted_payment_page_fields.py
killbill/models/hosted_payment_page_form_descriptor.py
killbill/models/invoice.py
killbill/models/invoice_dry_run.py
killbill/models/invoice_item.py
killbill/models/invoice_payment.py
killbill/models/invoice_payment_transaction.py
killbill/models/limit.py
killbill/models/node_command.py
killbill/models/node_command_property.py
killbill/models/overdue.py
killbill/models/overdue_condition.py
killbill/models/overdue_state.py
killbill/models/overdue_state_config.py
killbill/models/payment.py
killbill/models/payment_attempt.py
forestvpn_killbill-0.0.3.dist-info/METADATA
forestvpn_killbill-0.0.3.dist-info/WHEEL
forestvpn_killbill-0.0.3.dist-info/top_level.txt
forestvpn_killbill-0.0.3.dist-info/RECORD
